README.md
setup.py
pyrvsignal/__init__.py
pyrvsignal/signnal.py
pyrvsignal.egg-info/PKG-INFO
pyrvsignal.egg-info/SOURCES.txt
pyrvsignal.egg-info/dependency_links.txt
pyrvsignal.egg-info/not-zip-safe
pyrvsignal.egg-info/top_level.txt