Metadata-Version: 2.1
Name: pyrvsignal
Version: 2023.2.1
Summary: Signal for Python
Home-page: https://github.com/ravikiranb36/pyrvsignal.github.io.git
Author: Ravikirana B
Author-email: ravikiranb36@gmail.com
License: MIT
Keywords: Signal PySignal pyrvsignal pyqtsignal ThreadSafe Signal
Classifier: Programming Language :: Python :: 3
Classifier: License :: OSI Approved :: MIT License
Classifier: Operating System :: OS Independent
Requires-Python: >=3.6
